photoLA/__init__.py
photoLA/batch_LA.py
photoLA/calculate_LA.py
photoLA/single_LA.py
photoLA-1.0.0.dist-info/DESCRIPTION.rst
photoLA-1.0.0.dist-info/METADATA
photoLA-1.0.0.dist-info/RECORD
photoLA-1.0.0.dist-info/WHEEL
photoLA-1.0.0.dist-info/entry_points.txt
photoLA-1.0.0.dist-info/metadata.json
photoLA-1.0.0.dist-info/top_level.txt
