Metadata-Version: 2.0
Name: photoLA
Version: 1.0.0
Summary: Estimates Leaf Area from photographs using a direct relationship between pixel count of leaves and of a reference with known area.
Home-page: https://github.com/mattbv/photoLA
Author: Matheus Boni Vicari
Author-email: matheus.boni.vicari@gmail.com
License: LICENSE.txt
Keywords: Leaf Area photograph
Platform: UNKNOWN
Classifier: Programming Language :: Python
Classifier: Topic :: Scientific/Engineering
Requires-Dist: numpy (>=1.11.3)
Requires-Dist: pandas (>=0.20.1)
Requires-Dist: setuptools (>=36.0.1)
